dword/__init__.py
dword/_nbdev.py
dword/core.py
dword/utils.py
dword/tutorials/__init__.py
dword/tutorials/educational.py
dword/tutorials/sales.py
dword/tutorials/test_text2speech.py
dword/tutorials/test_video_actors.py
dword-0.0.9.dist-info/LICENSE
dword-0.0.9.dist-info/METADATA
dword-0.0.9.dist-info/WHEEL
dword-0.0.9.dist-info/entry_points.txt
dword-0.0.9.dist-info/top_level.txt
dword-0.0.9.dist-info/RECORD
