Metadata-Version: 2.1
Name: dword
Version: 0.0.9
Summary: Deep word utilities in Python
Home-page: https://github.com/deepword18/dword/tree/master/
Author: Deep Word
Author-email: contact@deepword.co
License: Apache Software License 2.0
Keywords: GAN video-generation
Platform: UNKNOWN
Classifier: Development Status :: 3 - Alpha
Classifier: Intended Audience :: Developers
Classifier: Natural Language :: English
Classifier: Programming Language :: Python :: 3.6
Classifier: Programming Language :: Python :: 3.7
Classifier: Programming Language :: Python :: 3.8
Classifier: License :: OSI Approved :: Apache Software License
Requires-Python: >=3.6
Requires-Dist: nbdev
Requires-Dist: notebook
Requires-Dist: ipython
Requires-Dist: requests
Requires-Dist: opencv-python
Requires-Dist: pytube
Requires-Dist: pydub
Requires-Dist: imageio
Requires-Dist: imageio-ffmpeg
Requires-Dist: fastcore
Requires-Dist: pandas
